[null,{"name":"clear","permissions":"ADMINISTRATOR","restriction":"0","actions":[{"info":"0","infoIndex":"1","storage":"1","varName":"amount","name":"Store Command Params"},{"storage":"1","varName":"amount","comparison":"1","iftrue":"0","iftrueVal":"","iffalse":"3","iffalseVal":"8","name":"Check Variable Type"},{"storage":"1","varName":"amount","comparison":"3","value":"0","iftrue":"3","iftrueVal":"7","iffalse":"0","iffalseVal":"","name":"Check Variable"},{"storage":"1","varName":"amount","comparison":"1","value":"1","iftrue":"0","iftrueVal":"","iffalse":"3","iffalseVal":"2","name":"Check Variable"},{"channel":"0","varName":"","message":"${member} No puedes eliminar 1 solo mensaje.","storage":"0","varName2":"","name":"Send Message"},{"name":"End Action Sequence"},{"channel":"0","count":"${tempVars(\"amount\")}","condition":"0","custom":"","varName":"","name":"Delete Bulk Messages"},{"storage":"0","varName":"","name":"Delete Message"},{"channel":"0","varName":"","message":"${member} :fire: »» ha borrado **${tempVars(\"amount\")}** mensajes!","storage":"1","varName2":"Burn","name":"Send Message"},{"time":"5","measurement":"1","name":"Wait"},{"storage":"1","varName":"Burn","name":"Delete Message"},{"name":"End Action Sequence"},{"channel":"0","varName":"","message":"Indica una cantidad válida. ","storage":"0","varName2":"","name":"Send Message"}],"_id":"AfXUk","comType":"0"},{"name":"bank","permissions":"NONE","restriction":"1","actions":[{"member":"1","varName":"","info":"2","storage":"1","varName2":"membername","name":"Store Member Info"},{"info":"0","infoIndex":"1","storage":"1","varName":"anyoneparam","name":"Store Command Params"},{"info":"0","infoIndex":"2","storage":"1","varName":"2param","name":"Store Command Params"},{"info":"0","infoIndex":"3","storage":"1","varName":"3param","name":"Store Command Params"},{"storage":"1","varName":"anyoneparam","comparison":"1","value":"\"donation\"","iftrue":"0","iftrueVal":"","iffalse":"2","iffalseVal":"12","name":"Check Variable"},{"title":"Bank Donation","author":"","color":"#42f468","timestamp":"false","url":"","authorIcon":"","imageUrl":"","thumbUrl":"","storage":"1","varName":"bankembeddonation","name":"Create Embed Message"},{"member":"1","varName":"","dataName":"money","comparison":"3","value":"100","iftrue":"1","iftrueVal":"","iffalse":"0","iffalseVal":"","name":"Check Member Data"},{"member":"1","varName":"","dataName":"money","changeType":"1","value":"-100","name":"Control Member Data"},{"storage":"1","varName":"bankembeddonation","message":"Hello ${tempVars(\"membername\")}! Just for using this command we have removed 100 U from your bank. It has gone to people of the moderation team.","name":"Set Embed Description"},{"storage":"1","varName":"bankembeddonation","channel":"0","varName2":"","name":"Send Embed Message"},{"name":"End Action Sequence"},{"storage":"1","varName":"anyoneparam","comparison":"1","value":"\"create\"","iftrue":"0","iftrueVal":"","iffalse":"2","iffalseVal":"20","name":"Check Variable"},{"member":"1","varName":"","dataName":"money","comparison":"1","value":"0","iftrue":"0","iftrueVal":"","iffalse":"2","iffalseVal":"59","name":"Check Member Data"},{"title":"Bank Account Creation","author":"","color":"#5ff442","timestamp":"false","url":"","authorIcon":"","imageUrl":"","thumbUrl":"","storage":"1","varName":"bankembedcreation","name":"Create Embed Message"},{"storage":"1","varName":"bankembedcreation","message":"Hello ${tempVars(\"membername\")}! Let's get you started with creating your bank account!\nI have went ahead and created it just now. You have been credited with 500 U to get you started.\n","name":"Set Embed Description"},{"member":"1","varName":"","dataName":"money","defaultVal":"0","storage":"2","varName2":"money","name":"Store Member Data"},{"member":"1","varName":"","dataName":"money","changeType":"0","value":"500","name":"Control Member Data"},{"storage":"1","varName":"bankembedcreation","channel":"0","varName2":"","name":"Send Embed Message"},{"name":"End Action Sequence"},{"storage":"1","varName":"anyoneparam","comparison":"1","value":"\"transfer\"","iftrue":"0","iftrueVal":"","iffalse":"2","iffalseVal":"29","name":"Check Variable"},{"title":"Bank Transfer","author":"","color":"#42e5f4","timestamp":"false","url":"","authorIcon":"","imageUrl":"","thumbUrl":"","storage":"1","varName":"bankembedbalance","name":"Create Embed Message"},{"member":"1","varName":"","dataName":"money","comparison":"4","value":"tempVars(\"3param\")","iftrue":"0","iftrueVal":"","iffalse":"1","iffalseVal":"27","name":"Check Member Data"},{"member":"0","varName":"","dataName":"money","changeType":"1","value":"tempVars(\"3param\")","name":"Control Member Data"},{"member":"1","varName":"","dataName":"money","changeType":"1","value":"-tempVars(\"3param\")","name":"Control Member Data"},{"storage":"1","varName":"bankembedbalance","message":"Hello ${tempVars(\"membername\")}! You have transferd money to ${mentionedUser}\n\nReciept:\nTransfered money: ${tempVars(\"3param\")}\nUsers involved: ${member} ${mentionedUser}\n\n\n","name":"Set Embed Description"},{"storage":"1","varName":"bankembedbalance","message":"Brick Bank Transfer Department","footerIcon":"","name":"Set Embed Footer"},{"storage":"1","varName":"bankembedbalance","channel":"0","varName2":"","name":"Send Embed Message"},{"name":"End Action Sequence"},{"storage":"1","varName":"anyoneparam","comparison":"1","value":"\"balance\"","iftrue":"0","iftrueVal":"","iffalse":"2","iffalseVal":"36","name":"Check Variable"},{"member":"0","varName":"","dataName":"money","defaultVal":"0","storage":"1","varName2":"bank balance","name":"Store Member Data"},{"title":"Bank Balance","author":"","color":"#3dff46","timestamp":"false","url":"","authorIcon":"","imageUrl":"","thumbUrl":"","storage":"1","varName":"bankbalanceembed","name":"Create Embed Message"},{"storage":"1","varName":"bankbalanceembed","message":"Checking Brick Bank Servers.... Ah I pulled it up here:\nUser: ${mentionedUser}\nUser Request by: ${member}\nBank Balance for mentioned user: ${tempVars(\"bank balance\")}\n","name":"Set Embed Description"},{"storage":"1","varName":"bankbalanceembed","message":"Brick Bank Balance Department","footerIcon":"","name":"Set Embed Footer"},{"storage":"1","varName":"bankbalanceembed","channel":"0","varName2":"","name":"Send Embed Message"},{"name":"End Action Sequence"},{"storage":"1","varName":"anyoneparam","comparison":"1","value":"\"loan\"","iftrue":"0","iftrueVal":"","iffalse":"2","iffalseVal":"48","name":"Check Variable"},{"member":"1","varName":"","dataName":"loan","comparison":"1","value":"1","iftrue":"2","iftrueVal":"46","iffalse":"0","iffalseVal":"","name":"Check Member Data"},{"member":"1","varName":"","dataName":"loan","defaultVal":"0","storage":"2","varName2":"loan","name":"Store Member Data"},{"member":"1","varName":"","dataName":"loan","changeType":"0","value":"1","name":"Control Member Data"},{"member":"1","varName":"","dataName":"money","changeType":"1","value":"1000","name":"Control Member Data"},{"title":"Bank Loans","author":"","color":"#23af07","timestamp":"false","url":"","authorIcon":"","imageUrl":"","thumbUrl":"","storage":"1","varName":"bankembedloans","name":"Create Embed Message"},{"storage":"1","varName":"bankembedloans","message":"Hello ${tempVars(\"membername\")}! We have went ahead and added 1,000 U to your account to spend and afford higher priced items or games.\nPlease be sure to pay the bank back as you won't be able to take another loan out. \nAlso some games and stuff may prevent you from playing as you have loan's to pay off.","name":"Set Embed Description"},{"storage":"1","varName":"bankembedloans","message":"Brick Bank Loan Department","footerIcon":"","name":"Set Embed Footer"},{"storage":"1","varName":"bankembedloans","channel":"0","varName2":"","name":"Send Embed Message"},{"name":"End Action Sequence"},{"channel":"0","varName":"","message":"You currently already have a loan with us. Please pay that off before getting a new loan!","storage":"0","varName2":"","name":"Send Message"},{"name":"End Action Sequence"},{"storage":"1","varName":"anyoneparam","comparison":"1","value":"\"payloan\"","iftrue":"0","iftrueVal":"","iffalse":"2","iffalseVal":"62","name":"Check Variable"},{"member":"1","varName":"","dataName":"loan","comparison":"1","value":"1","iftrue":"0","iftrueVal":"","iffalse":"2","iffalseVal":"60","name":"Check Member Data"},{"title":"Pay Bank Loan","author":"","color":"#69af07","timestamp":"false","url":"","authorIcon":"","imageUrl":"","thumbUrl":"","storage":"1","varName":"payloanembed","name":"Create Embed Message"},{"member":"1","varName":"","dataName":"money","comparison":"3","value":"1000","iftrue":"2","iftrueVal":"59","iffalse":"0","iffalseVal":"59","name":"Check Member Data"},{"member":"1","varName":"","dataName":"money","changeType":"1","value":"-1000","name":"Control Member Data"},{"member":"1","varName":"","dataName":"loan","changeType":"0","value":"0","name":"Control Member Data"},{"storage":"1","varName":"payloanembed","message":"Hello ${tempVars(\"membername\")}! You have successfully paid off your loan.\nYou are allowed to have another loan with us and until you take another loan out, you will be able to play all minigames and be able to buy anything again.","name":"Set Embed Description"},{"storage":"1","varName":"payloanembed","message":"Brick Bank Loan Payment Department","footerIcon":"","name":"Set Embed Footer"},{"storage":"1","varName":"payloanembed","channel":"0","varName2":"","name":"Send Embed Message"},{"name":"End Action Sequence"},{"channel":"0","varName":"","message":"You currently don't have any loans with us.\n","storage":"0","varName2":"","name":"Send Message"},{"name":"End Action Sequence"},{"channel":"0","varName":"","message":"You currently do not have the funds to pay off your loan. Please get more cash to pay the loan off!\n\n","storage":"0","varName2":"","name":"Send Message"},{"name":"End Action Sequence"},{"storage":"1","varName":"anyoneparam","comparison":"1","value":"\"help\"","iftrue":"0","iftrueVal":"","iffalse":"1","iffalseVal":"","name":"Check Variable"},{"title":"Bank Help","author":"","color":"#42f468","timestamp":"false","url":"","authorIcon":"","imageUrl":"","thumbUrl":"","storage":"1","varName":"bankhelpembed2","name":"Create Embed Message"},{"storage":"1","varName":"bankhelpembed2","message":"Hello ${tempVars(\"membername\")}! Welcome to the Brick bank. You have reached the help department.\nPlease read **closely** as are menu options may have changed..\n\nFor new members and/or people who want to start fresh with a new bank account, type *bank create\nFor donating to the moderators type *bank donation\nFor transfering money to another user type *bank transfer \nFor seeing your balance or other user's type *bank balance @usermention\nFor getting a loan type *bank loan\nFor paying off a loan type *bank payloan\nFor seeing this help menu type *bank help\n","name":"Set Embed Description"},{"storage":"1","varName":"bankhelpembed2","channel":"0","varName2":"","name":"Send Embed Message"},{"name":"End Action Sequence"}],"comType":"0","_id":"TZata"},{"name":"clearchat","permissions":"ADMINISTRATOR","restriction":"0","actions":[{"channel":"0","count":"10000","condition":"0","custom":"","varName":"","name":"Delete Bulk Messages"},{"storage":"0","varName":"","name":"Delete Message"},{"channel":"0","varName":"","message":"${member} :fire: »» ha eliminado **todos** los mensajes de las últimas 2 semanas.","storage":"1","varName2":"fire","name":"Send Message"},{"time":"5","measurement":"1","name":"Wait"},{"storage":"1","varName":"fire","name":"Delete Message"}],"_id":"JlJNY"},{"name":"donar","permissions":"NONE","restriction":"0","_id":"APuwZ","actions":[{"channel":"0","varName":"","message":"Dale una taza de café al developer del bot :heart:\n\n**https://paypal.me/panbimbogd**","storage":"0","varName2":"","name":"Send Message"},{"storage":"0","varName":"","name":"Delete Message"}]},{"name":"ayuda","permissions":"NONE","restriction":"0","_id":"GiVEQ","actions":[{"channel":"0","varName":"","message":"Bot creado por: **PanbimboGD#2451**\n\n```css\nComandos:\n\n+clear X (Necesitas permiso de administrador)\n\n+clearchat (Necesitas permiso de administrador)\n\n+play X\n\n+dados\n\n+donar```","storage":"0","varName2":"","name":"Send Message"},{"storage":"0","varName":"","name":"Delete Message"}]},{"name":"dados","permissions":"NONE","restriction":"1","_id":"yPFZM","actions":[{"storage":"1","varName":"dados","min":"1","max":"6","name":"Generate Random Number"},{"channel":"0","varName":"","message":"${member} ha tirado los dados y a sacado un **${tempVars(\"dados\")}**!","storage":"0","varName2":"","name":"Send Message"},{"name":"End Action Sequence"}],"comType":"0"},{"name":"play","permissions":"NONE","restriction":"1","_id":"pHvtR","actions":[{"storage":"0","varName":"","name":"Delete Message"},{"condition":"0","comparison":"0","value":"0","iftrue":"0","iftrueVal":"","iffalse":"3","iffalseVal":"5","name":"Check Parameters"},{"channel":"0","varName":"","message":"You need to enter a song name or YouTube link!","storage":"1","varName2":"nolink","name":"Send Message"},{"time":"5","measurement":"1","name":"Wait"},{"storage":"1","varName":"nolink","name":"Delete Message"},{"time":"5","measurement":"1","name":"Wait"},{"name":"End Action Sequence"},{"iftrue":"3","iftrueVal":"1","iffalse":"0","iffalseVal":"1","name":"Check is Bot in Voice Channel"},{"channel":"0","varName":"","name":"Join Voice Channel"},{"info":"1","infoIndex":"1","storage":"1","varName":"songyt","name":"Store Command Params"},{"token":"","user":"","pass":"","url":"https://www.googleapis.com/youtube/v3/search?part=snippet&q=${tempVars(\"songyt\")}&type=video&key=AIzaSyDLaF8YLV29VygfmUE_OugxKCrvs9qd5Sg","path":"items[0].snippet.title","storage":"1","varName":"sr-y-1","debugMode":"1","headers":"","name":"Store Json From WebAPI"},{"token":"","user":"","pass":"","url":"https://www.googleapis.com/youtube/v3/search?part=snippet&q=${tempVars(\"songyt\")}&type=video&key=AIzaSyDLaF8YLV29VygfmUE_OugxKCrvs9qd5Sg","path":"items[0].id.videoId","storage":"1","varName":"sid-y-1","debugMode":"1","headers":"","name":"Store Json From WebAPI"},{"token":"","user":"","pass":"","url":"https://www.googleapis.com/youtube/v3/search?part=snippet&q=${tempVars(\"songyt\")}&type=video&key=AIzaSyDLaF8YLV29VygfmUE_OugxKCrvs9qd5Sg","path":"items[0].snippet.thumbnails.high.url","storage":"1","varName":"stn-y-1","debugMode":"1","headers":"","name":"Store Json From WebAPI"},{"token":"","user":"","pass":"","url":"https://www.googleapis.com/youtube/v3/videos?id=${tempVars(\"sid-y-1\")}&part=contentDetails&key=AIzaSyDLaF8YLV29VygfmUE_OugxKCrvs9qd5Sg","path":"items[0].contentDetails.duration","storage":"1","varName":"sd-y-1","debugMode":"1","headers":"","name":"Store Json From WebAPI"},{"ytTime":"${tempVars(\"sd-y-1\")}","storage":"1","varName":"sd-c-y-1","name":"YouTube Time Converter"},{"url":"${tempVars(\"sid-y-1\")}","seek":"0","volume":"60","passes":"1","bitrate":"192","type":"0","name":"Play YouTube Video"},{"server":"0","varName":"","dataName":"playing","comparison":"1","value":"1","iftrue":"2","iftrueVal":"34","iffalse":"0","iffalseVal":"1","name":"Check Server Data"},{"title":"","author":"Now Playing","color":"#5cd9ed","timestamp":"true","url":"","authorIcon":"${serverVars(\"server-icon\")}","imageUrl":"","thumbUrl":"${tempVars(\"stn-y-1\")}","storage":"1","varName":"playembed","name":"Create Embed Message"},{"storage":"1","varName":"playembed","message":"${tempVars(\"sr-y-1\")}","name":"Set Embed Description"},{"storage":"1","varName":"playembed","fieldName":"Link","message":"https://youtube.com/watch?v=${tempVars(\"sid-y-1\")}","inline":"0","name":"Add Embed Field"},{"storage":"1","varName":"playembed","channel":"0","varName2":"","name":"Send Embed Message"},{"server":"0","varName":"","dataName":"playing","changeType":"0","value":"1","name":"Control Server Data"},{"server":"0","varName":"","dataName":"playing-count","changeType":"1","value":"1","name":"Control Server Data"},{"storage":"2","varName":"queue","name":"Create List"},{"storage":"2","varName":"queue-id","name":"Create List"},{"storage":"2","varName":"queue-id","addType":"0","position":"","value":"tempVars(\"sid-y-1\")","name":"Add Item to List"},{"storage":"2","varName":"queue","addType":"0","position":"","value":"tempVars(\"sr-y-1\")","name":"Add Item to List"},{"title":"","author":"Now Playing","color":"#5cd9ed","timestamp":"true","url":"","authorIcon":"${serverVars(\"server-icon\")}","imageUrl":"","thumbUrl":"${tempVars(\"stn-y-2\")}","storage":"1","varName":"playembed","name":"Create Embed Message"},{"storage":"1","varName":"playembed","message":"${tempVars(\"sr-y-2\")}","name":"Set Embed Description"},{"storage":"1","varName":"playembed","fieldName":"Link","message":"https://youtube.com/watch?v=${tempVars(\"sid-y-2\")}","inline":"0","name":"Add Embed Field"},{"server":"0","varName":"","dataName":"playing-count","comparison":"1","value":"1","iftrue":"0","iftrueVal":"","iffalse":"1","iffalseVal":"","name":"Check Server Data"},{"source":"com-7","type":"true","name":"Call Command/Event"},{"name":"End Action Sequence"},{"storage":"2","varName":"queue-id","addType":"0","position":"","value":"tempVars(\"sid-y-1\")","name":"Add Item to List"},{"storage":"2","varName":"queue","addType":"0","position":"","value":"tempVars(\"sr-y-1\")","name":"Add Item to List"},{"title":"","author":"Added to Queue","color":"#5cd9ed","timestamp":"true","url":"","authorIcon":"${serverVars(\"server-icon\")}","imageUrl":"","thumbUrl":"${tempVars(\"stn-y-1\")}","storage":"1","varName":"playembed","name":"Create Embed Message"},{"storage":"1","varName":"playembed","message":"${tempVars(\"sr-y-1\")}","name":"Set Embed Description"},{"storage":"1","varName":"playembed","fieldName":"Link","message":"https://youtube.com/watch?v=${tempVars(\"sid-y-1\")}","inline":"0","name":"Add Embed Field"},{"storage":"1","varName":"playembed","channel":"0","varName2":"","name":"Send Embed Message"},{"server":"0","varName":"","dataName":"playing-count","changeType":"1","value":"1","name":"Control Server Data"},{"server":"0","varName":"","dataName":"playing-count","comparison":"1","value":"1","iftrue":"0","iftrueVal":"","iffalse":"1","iffalseVal":"","name":"Check Server Data"},{"source":"com-7","type":"true","name":"Call Command/Event"}],"comType":"0","_aliases":[]},{"name":"levelsystem","permissions":"NONE","restriction":"4","actions":[{"storage":"1","varName":"ExperienceRate","min":"1","max":"17","name":"Generate Random Number"},{"message":"0","varName":"msg","info":"3","storage":"2","varName2":"member","name":"Store Message Info"},{"member":"3","varName":"member","dataName":"exp","changeType":"1","value":"tempVars(\"ExperienceRate\")","name":"Control Member Data"},{"member":"3","varName":"member","dataName":"level","defaultVal":"1","storage":"2","varName2":"myLevel","name":"Store Member Data"},{"member":"3","varName":"member","dataName":"exp","comparison":"4","value":"${serverVars(\"myLevel\") * 50}","iftrue":"0","iftrueVal":"","iffalse":"1","iffalseVal":"","name":"Check Member Data"},{"member":"3","varName":"member","dataName":"exp","changeType":"0","value":"0","name":"Control Member Data"},{"member":"3","varName":"member","dataName":"level","changeType":"1","value":"1","name":"Control Member Data"},{"message":"2","varName":"msg","info":"4","storage":"1","varName2":"channel","name":"Store Message Info"},{"member":"3","varName":"member","dataName":"level","defaultVal":"1","storage":"2","varName2":"myLevel","name":"Store Member Data"},{"member":"1","varName":"","dataName":"Credit","defaultVal":"0","storage":"2","varName2":"myCredit","name":"Store Member Data"},{"storage":"1","varName":"RewardCredit","min":"100","max":"700","name":"Generate Random Number"},{"member":"1","varName":"","dataName":"Credit","changeType":"1","value":"tempVars(\"RewardCredit\")","name":"Control Member Data"},{"channel":"0","varName":"Leveler","message":"**「Level System」**\nー${serverVars(\"member\")} ha alcanzado el nivel ${serverVars(\"myLevel\")}.\nーSiguiente nivel en ${serverVars(\"myLevel\") * 5} experiencia.\nーTe hemos dado ${tempVars(\"RewardCredit\")} creditos por subir de nivel.","storage":"1","varName2":"CurrentLevel","name":"Send Message"},{"time":"1","measurement":"2","name":"Wait"},{"storage":"1","varName":"CurrentLevel","name":"Delete Message"}],"comType":"3","_id":"TODXq"},{"name":"creditos","permissions":"NONE","restriction":"4","_id":"JZoIB","actions":[{"channel":"0","varName":"","message":"Tienes ${serverVars(\"myCredit\")} créditos.","storage":"0","varName2":"","name":"Send Message"}],"comType":"0"},{"name":"verificar","permissions":"NONE","restriction":"1","_id":"yEdhi","actions":[{"info":"1","find":"Usuario","storage":"1","varName":"rank","name":"Find Role"},{"info":"1","find":"Nuevo","storage":"1","varName":"new","name":"Find Role"},{"info":"0","find":"484169050797375501","storage":"1","varName":"bienvenida","name":"Find Channel"},{"member":"1","varName2":"","role":"3","varName":"rank","name":"Add Member Role"},{"member":"1","varName2":"","role":"3","varName":"new","name":"Remove Member Role"},{"channel":"5","varName":"bienvenida","message":"🎉 ${member} Bienvenido a **Bimbo's Lounge**. Diviértete! 🎉","storage":"0","varName2":"","name":"Send Message"}]}]